[
  {
    "name": "Hsu"
  },
  [
    {
      "t": "#000000\n\n#0000FF\n#0000FF",
      "f": 5
    },
    "&nbsp;~\n&nbsp;`",
    "!\n1",
    "@\n2",
    "#\n3",
    "$\n4",
    "%\n5",
    "^\n6",
    "&\n7",
    "*\n8",
    "(\n9",
    ")\n0",
    "_\n-",
    "+\n=",
    {
      "t": "#000000",
      "a": 6,
      "f": 3,
      "fa": [
        4
      ],
      "w": 2
    },
    "&nbsp;Backspace"
  ],
  [
    {
      "w": 1.5
    },
    "&nbsp;Tab",
    {
      "t": "#000000\n\n#0000FF\n#0000FF",
      "a": 4,
      "f": 5
    },
    "Q",
    "W\n\nㄠ",
    "E\n\nㄧ\nㄝ",
    "R\n\nㄖ",
    "T\n\nㄊ",
    "Y\n\nㄚ",
    "U\n\nㄩ",
    "I\n\nㄞ",
    "O\n\nㄡ",
    "P\n\nㄆ",
    "{\n[",
    "}\n]",
    {
      "w": 1.5
    },
    "&nbsp;|\n&nbsp;\\"
  ],
  [
    {
      "t": "#000000",
      "a": 6,
      "f": 3,
      "fa": [
        4
      ],
      "w": 1.75
    },
    "&nbsp;Caps Lock",
    {
      "t": "#000000\n\n#0000FF\n#0000FF",
      "a": 4,
      "f": 5
    },
    "A\n\nㄘ\nㄟ",
    "S\n\nㄙ\n˙",
    "D\n\nㄉ\nˊ",
    "F\n\nㄈ\nˇ",
    "G\n\nㄍ\nㄜ",
    "H\n\nㄏ\nㄛ",
    {
      "t": "#000000\n#0000FF\n#0000FF\n#0000FF"
    },
    "J\nˋ\nㄐ\nㄓ",
    {
      "t": "#000000\n\n#0000FF\n#0000FF"
    },
    "K\n\nㄎ\nㄤ",
    {
      "t": "#000000\n#0000FF\n#0000FF\n#0000FF"
    },
    "L\nㄦ\nㄌ\nㄥ",
    {
      "t": "#000000\n\n#0000FF\n#0000FF"
    },
    ":\n;",
    "\"\n'",
    {
      "t": "#000000",
      "a": 6,
      "f": 3,
      "fa": [
        4
      ],
      "w": 2.25
    },
    "&nbsp;Enter"
  ],
  [
    {
      "w": 2.25
    },
    "&nbsp;Shift",
    {
      "t": "#000000\n\n#0000FF\n#0000FF",
      "a": 4,
      "f": 5
    },
    "Z\n\nㄗ",
    "X\n\nㄨ",
    "C\n\nㄒ\nㄕ",
    "V\n\nㄑ\nㄕ",
    "B\n\nㄅ",
    "N\n\nㄋ\nㄣ",
    "M\n\nㄇ\nㄢ",
    "<\n,",
    ">\n.",
    "?\n/",
    {
      "t": "#000000",
      "a": 6,
      "f": 3,
      "fa": [
        4
      ],
      "w": 2.75
    },
    "&nbsp;Shift"
  ],
  [
    {
      "w": 1.25
    },
    "&nbsp;Ctrl",
    {
      "a": 7,
      "fa": [
        7
      ],
      "w": 1.25
    },
    "<i class='fa fa-windows'></i>",
    {
      "a": 6,
      "fa": [
        4
      ],
      "w": 1.25
    },
    "&nbsp;Alt",
    {
      "a": 7,
      "w": 6
    },
    "",
    {
      "a": 6,
      "w": 1.25
    },
    "&nbsp;Alt",
    {
      "a": 7,
      "fa": [
        7
      ],
      "w": 1.25
    },
    "<i class='fa fa-windows'></i>",
    {
      "w": 1.25
    },
    "<i class='fa fa-reorder'></i>",
    {
      "a": 6,
      "fa": [
        4
      ],
      "w": 1.5
    },
    "&nbsp;Ctrl"
  ]
]